Workbook

Sheet Филиалы
A1: Статья движения денежных средств | B1: Сумма | C1: Получатель | D1: Заявка | E1: Дата заявки | F1: Статус | G1: Организация | H1: Подразделение | I1: Приоритет | J1: Назначение платежа | K1: Дата оплаты | L1: Заявитель
A2: Оплата поставщикам Прочие поставщики 4121 | B2: 10185 | C2: Абулхаиров Ренат Рафаилович ИП | D2: СИ00-033695 | E2: 01.09.2026 7:48:29 | F2: Согласована | G2: Сервис-Интегратор ООО | H2: ДТ ТОБОЛЬСК | I2: Стандартный | J2: Оплата по накладной №003683 от 05.08.2026 10185-00 руб. В т.ч. НДС (5%) 485-00 руб. | K2: 46273 | L2: Силин Никита Сергеевич | M2: =MATCH(D:D,'Оплаты в рамках 100 т.р.'!D:D,0) -> #N/A
A3: Оплата поставщикам Прочие поставщики 4121 | B3: 16500 | C3: АВТОКОНТРОЛЬ ООО | D3: СИ00-025734 | E3: 09.07.2026 22:17:34 | F3: Согласована | G3: Сервис-Интегратор ООО | H3: ДТ КАЗАНЬ | I3: Стандартный | J3: Оплата по договору №04/03-2024К от 21.03.2024 16500-00 В т.ч. НДС (22%) 2975-41 руб. | K3: 46218 | L3: Хакимов Рифат Рашатович | M3: =MATCH(D:D,'Оплаты в рамках 100 т.р.'!D:D,0) -> #N/A
A4: Оплата поставщикам Прочие поставщики 4121 | B4: 11000 | C4: АВТОКОНТРОЛЬ ООО | D4: СИ00-031230 | E4: 13.08.2026 22:00:31 | F4: Согласована | G4: Сервис-Интегратор ООО | H4: ДТ КАЗАНЬ | I4: Стандартный | J4: Оплата по договору №04/03-2024К от 21.03.2024 11000-00 В т.ч. НДС (22%) 1983-61 руб. | K4: 46253 | L4: Хакимов Рифат Рашатович | M4: =MATCH(D:D,'Оплаты в рамках 100 т.р.'!D:D,0) -> #N/A
A5: Оплата поставщикам Прочие поставщики 4121 | B5: 46500 | C5: АВТОКОНТРОЛЬ ООО | D5: СИ00-029057 | E5: 31.07.2026 22:00:34 | F5: Согласована | G5: Сервис-Интегратор ООО | H5: ДТ КАЗАНЬ | I5: Стандартный | J5: Оплата по договору №04/04-26А от 22.04.2026 46500-00 В т.ч. НДС (22%) 8385-24 руб. | K5: 46240 | L5: Хакимов Рифат Рашатович | M5: =MATCH(D:D,'Оплаты в рамках 100 т.р.'!D:D,0) -> #N/A
A6: Оплата поставщикам Прочие поставщики 4121 | B6: 18500 | C6: АВТОКОНТРОЛЬ ООО | D6: СИ00-027381 | E6: 21.07.2026 22:00:15 | F6: Согласована | G6: Сервис-Интегратор ООО | H6: ДТ КАЗАНЬ | I6: Стандартный | J6: Оплата по договору №04/03-2024К от 21.03.2024 18500-00 В т.ч. НДС (22%) 3336-07 руб. | K6: 46230 | L6: Хакимов Рифат Рашатович | M6: =MATCH(D:D,'Оплаты в рамках 100 т.р.'!D:D,0) -> #N/A
A7: Оплата поставщикам Прочие поставщики 4121 | B7: 12500 | C7: Автотранспортное предприятие ООО | D7: СИ00-032229 | E7: 20.08.2026 14:43:29 | F7: Согласована | G7: Сервис-Интегратор ООО | H7: ДТ КАЗАНЬ | I7: Стандартный | J7: Оплата по Договору на оказание услуг (предрейсового (послерейсового) осмотра водителей) от 01.01.2026 12500-00 руб. Без налога (НДС) | K7: 46254 | L7: Шайхиева Любовь Игоревна | M7: =MATCH(D:D,'Оплаты в рамках 100 т.р.'!D:D,0) -> #N/A
A8: Оплата поставщикам Прочие поставщики 4121 | B8: 32000 | C8: АЛГОРИТМ ЭКСПЕРТИЗЫ ТРУДА ООО | D8: СИ00-035040 | E8: 09.09.2026 9:57:03 | F8: Согласована | G8: Сервис-Интегратор ООО | H8: ДТ НОВЫЙ УРЕНГОЙ | I8: Стандартный | J8: Счет № 138-ОБ от 09.09.26, 32 000- руб Обучение охрана труда Б; В (пожароопасные работы); В (работа на высоте); СИЗ; ПП; работа на высоте с присвоением 2 группы | K8: 46274 | L8: Фукс Елена Владимировна | M8: =MATCH(D:D,'Оплаты в рамках 100 т.р.'!D:D,0) -> #N/A
A9: Оплата поставщикам Прочие поставщики 4121 | B9: 32000 | C9: АЛГОРИТМ ЭКСПЕРТИЗЫ ТРУДА ООО | D9: СИ00-034847 | E9: 08.09.2026 10:33:35 | F9: Согласована | G9: Сервис-Интегратор ООО | H9: ДТ НОВЫЙ УРЕНГОЙ | I9: Стандартный | J9: Счет № 134-ОБ от 17.08.26, 32 000- руб Обучение охрана труда Б; В (пожароопасные работы); В (работа на высоте); СИЗ; ПП; работа на высоте с присвоением 2 группы | K9: 46273 | L9: Фукс Елена Владимировна | M9: =MATCH(D:D,'Оплаты в рамках 100 т.р.'!D:D,0) -> #N/A
A10: Оплата поставщикам Прочие поставщики 4121 | B10: 16500 | C10: АЛГОРИТМ ЭКСПЕРТИЗЫ ТРУДА ООО | D10: СИ00-034734 | E10: 07.09.2026 16:58:35 | F10: Согласована | G10: Сервис-Интегратор ООО | H10: ДТ ТУРУХАНСК | I10: Стандартный | J10: Оплата согласно Договору № 006/ОБ от 08 августа 2024г. на оказание услуги. Обучение по программе:Водитель КМУ, слесарь- электрик, слесарь по ремонту Счет № 136-ОБ от 07.09.2026 г на 16 500 руб. Без НДС | K10: 46273 | L10: Малясова Анастасия Ивановна | M10: =MATCH(D:D,'Оплаты в рамках 100 т.р.'!D:D,0) -> #N/A
A11: Оплата поставщикам Прочие поставщики 4121 | B11: 22000 | C11: АЛГОРИТМ ЭКСПЕРТИЗЫ ТРУДА ООО | D11: СИ00-035967 | E11: 14.09.2026 15:04:02 | F11: Согласована | G11: Сервис-Интегратор ООО | H11: ДТ ТУРУХАНСК | I11: Стандартный | J11: Оплата согласно Договору № 006/ОБ от 08 августа 2024г. на оказание услуги. Обучение по программе:Машинист КМУ-2 чел,водитель погр, слесарь Счет № 140-ОБ от 11.09.2026 г на 22 000 руб. Без НДС | K11: 46280 | L11: Малясова Анастасия Ивановна | M11: =MATCH(D:D,'Оплаты в рамках 100 т.р.'!D:D,0) -> #N/A
A12: Оплата поставщикам Прочие поставщики 4121 | B12: 311307.8 | C12: АЛГОРИТМИКС ООО | D12: СИ00-035069 | E12: 09.09.2026 12:25:25 | F12: Согласована | G12: Сервис-Интегратор ООО | H12: ДТ ЭЛЬГА | I12: Стандартный | J12: Оплата по Спецификациям Договора поставки №3 от 21.01.2019 (по накл.) 311307-80 руб. В т.ч. НДС (22%) 56137-47 руб. | K12: 46274 | L12: Павлин Александр Иванович | M12: =MATCH(D:D,'Оплаты в рамках 100 т.р.'!D:D,0) -> #N/A
A13: Оплата поставщикам Запчасти, ремонт 4121 | B13: 67680 | C13: Андриенко Дмитрий Викторович ИП | D13: СИ00-014080 | E13: 17.04.2026 7:27:02 | F13: Согласована | G13: Сервис-Интегратор ООО | H13: ДТ ТУРУХАНСК | I13: Стандартный | J13: Оплата по Оплата по Спецификациям Договора поставки от 17.02.2025 67680-00 руб. В т.ч. НДС (22%) 12204-59 руб. Форсунки С294НР797 СПУ | K13: 46129 | L13: Лапин Андрей Геннадьевич | M13: =MATCH(D:D,'Оплаты в рамках 100 т.р.'!D:D,0) -> #N/A
... A67: Оплата поставщикам Аренда помещений, коммунальные платежи и связь 4121 | B67: 7060.97 | C67: НОП СИБИРЬ-ТНХ ООО | D67: СИ00-034663 | E67: 07.09.2026 8:39:53 | F67: Согласована | G67: Сервис-Интегратор ООО | H67: ДТ ТОБОЛЬСК | I67: Стандартный | J67: Оплата по накладной №900 от 31.08.2026 7060-97 руб. В т.ч. НДС (22%) 1273-29 руб. | K67: 46281 | L67: Канаева Ирина Андреевна | M67: =MATCH(D:D,'Оплаты в рамках 100 т.р.'!D:D,0) -> #N/A
A68: Оплата поставщикам Спецодежда 4121 | B68: 42330 | C68: АЙКОН ООО | D68: СИ00-036485 | E68: 16.09.2026 16:59:28 | F68: Согласована | G68: Сервис-Интегратор ООО | H68: ДТ МОСКВА | I68: Стандартный | J68: Оплата по Счет-договор № 208 от 08.09.2026 42330-00 руб. В т.ч. НДС (22%) 7633-28 руб. | K68: 17.09.2026 | L68: Понаськов Александр Анатольевич | M68: =MATCH(D:D,'Оплаты в рамках 100 т.р.'!D:D,0) -> #N/A
A69: Оплата поставщикам Прочие поставщики 4121 | B69: 50000 | C69: ТЕХНОЛОГИИ УМНОЙ МОБИЛЬНОСТИ ООО | D69: СИ00-036486 | E69: 16.09.2026 17:10:46 | F69: Согласована | G69: Сервис-Интегратор ООО | H69: ДТ МОСКВА | I69: Стандартный | J69: Оплата по Договор № FMS/01/2704-26 от 01.05.2026 по счету № 32904532 от 16.09.2026 на 50000-00 руб. Без налога (НДС) | K69: 17.09.2026 | L69: Понаськов Александр Анатольевич | M69: =MATCH(D:D,'Оплаты в рамках 100 т.р.'!D:D,0) -> #N/A
A73: Сводная таблица оплат по подразделениям
A75: Контрагент | B75: ДТ БУРЯТИЯ | C75: ДТ КАЗАНЬ | D75: ДТ КРАСНОЯРСК | E75: ДТ КУЗБАСС | F75: ДТ КУЮМБА | G75: ДТ МОСКВА | H75: ДТ МУРАВЛЕНКО | I75: ДТ НОВЫЙ УРЕНГОЙ | J75: ДТ ОМСК | K75: ДТ ТОБОЛЬСК | L75: ДТ ТУРУХАНСК | M75: ДТ УК | N75: ДТ ХАКАСИЯ | O75: ДТ ЭЛЬГА | P75: Итого | Q75: Пояснение
A76: АВТОКОНТРОЛЬ ООО | B76: 0 | C76: 92500 | D76: 0 | E76: 0 | F76: 0 | G76: 0 | H76: 0 | I76: 0 | J76: 0 | K76: 0 | L76: 0 | M76: 0 | N76: 0 | O76: 0 | P76: 92500 | Q76: Оформление карт тахографа, поставка СКЗИ
A77: АЙКОН ООО | B77: 0 | C77: 0 | D77: 0 | E77: 0 | F77: 0 | G77: 42330 | H77: 0 | I77: 0 | J77: 0 | K77: 0 | L77: 0 | M77: 0 | N77: 0 | O77: 0 | P77: 42330 | Q77: Спецодежда
A78: АЛГОРИТМ ЭКСПЕРТИЗЫ ТРУДА ООО | B78: 0 | C78: 0 | D78: 0 | E78: 0 | F78: 0 | G78: 0 | H78: 0 | I78: 64000 | J78: 0 | K78: 0 | L78: 38500 | M78: 0 | N78: 0 | O78: 0 | P78: 102500 | Q78: Обучение
A79: АЛГОРИТМИКС ООО | B79: 0 | C79: 0 | D79: 0 | E79: 0 | F79: 0 | G79: 0 | H79: 0 | I79: 0 | J79: 0 | K79: 0 | L79: 0 | M79: 0 | N79: 0 | O79: 311307.8 | P79: 311307.8 | Q79: Закупка ТМЦ
A80: АСН-ЛИФТ ООО | B80: 0 | C80: 31720 | D80: 0 | E80: 0 | F80: 0 | G80: 0 | H80: 0 | I80: 0 | J80: 0 | K80: 0 | L80: 0 | M80: 0 | N80: 0 | O80: 0 | P80: 31720 | Q80: Обслуживание лифтов
A81: Абулхаиров Ренат Рафаилович ИП | B81: 0 | C81: 0 | D81: 0 | E81: 0 | F81: 0 | G81: 0 | H81: 0 | I81: 0 | J81: 0 | K81: 10185 | L81: 0 | M81: 0 | N81: 0 | O81: 0 | P81: 10185 | Q81: Техосмотры
A82: Автотранспортное предприятие ООО | B82: 0 | C82: 12500 | D82: 0 | E82: 0 | F82: 0 | G82: 0 | H82: 0 | I82: 0 | J82: 0 | K82: 0 | L82: 0 | M82: 0 | N82: 0 | O82: 0 | P82: 12500 | Q82: Медосмотры
A83: Андриенко Дмитрий Викторович ИП | B83: 0 | C83: 0 | D83: 0 | E83: 0 | F83: 0 | G83: 0 | H83: 0 | I83: 0 | J83: 0 | K83: 0 | L83: 67680 | M83: 0 | N83: 0 | O83: 0 | P83: 67680 | Q83: Закупка ТМЦ
A84: БУБОРГ-ОСТ ООО | B84: 0 | C84: 0 | D84: 0 | E84: 0 | F84: 10500 | G84: 0 | H84: 0 | I84: 0 | J84: 0 | K84: 0 | L84: 2800 | M84: 0 | N84: 0 | O84: 0 | P84: 13300 | Q84: Изготовление госномеров
A85: Бахтараев Василий Борисович ИП | B85: 0 | C85: 0 | D85: 0 | E85: 0 | F85: 0 | G85: 0 | H85: 0 | I85: 0 | J85: 0 | K85: 0 | L85: 0 | M85: 0 | N85: 600 | O85: 0 | P85: 600 | Q85: Расходы IT
A86: Бочкарев Евгений Евгеньевич ИП | B86: 0 | C86: 0 | D86: 0 | E86: 0 | F86: 0 | G86: 0 | H86: 0 | I86: 0 | J86: 0 | K86: 0 | L86: 0 | M86: 0 | N86: 4875 | O86: 0 | P86: 4875 | Q86: Мойка ТС/Шиномонтаж
A87: ВТОРЭКОСЕРВИС ООО | B87: 0 | C87: 0 | D87: 0 | E87: 950 | F87: 0 | G87: 0 | H87: 0 | I87: 0 | J87: 0 | K87: 0 | L87: 0 | M87: 0 | N87: 0 | O87: 0 | P87: 950 | Q87: Аренда контейнера
... A124: ЭТАЛОН-СЕРВИС ООО | B124: 0 | C124: 0 | D124: 0 | E124: 2000 | F124: 0 | G124: 0 | H124: 0 | I124: 0 | J124: 0 | K124: 0 | L124: 0 | M124: 0 | N124: 0 | O124: 0 | P124: 2000 | Q124: ТО пожарной сигнализации
A125: ИТОГО | B125: 8200 | C125: 329284.15 | D125: 2500 | E125: 88970 | F125: 325496 | G125: 109130 | H125: 424440 | I125: 64000 | J125: 13800 | K125: 17245.97 | L125: 613536.89 | M125: 12370.8 | N125: 113168 | O125: 480001.64 | P125: 2602143.5
P129: =P125+УК!I36+'Жилье, питание, связь, аренда'!O74+'Непереносимые оплаты'!H20+'Оплаты в рамках 100 т.р.'!D21+График!O76+Согласовано!H43 -> 16985052

Sheet УК
A1: Статья движения денежных средств | B1: Сумма | C1: Получатель | D1: Заявка | E1: Дата заявки | F1: Статус | G1: Организация | H1: Подразделение | I1: Приоритет | J1: Назначение платежа | K1: Дата оплаты | L1: Заявитель
A2: Оплата поставщикам Прочие поставщики 4121 | B2: 10000 | C2: АРКАДА ООО | D2: СИ00-034698 | E2: 07.09.2026 11:54:56 | F2: Согласована | G2: Сервис-Интегратор ООО | H2: ДТ НОВЫЙ УРЕНГОЙ | I2: Стандартный | J2: Оплата по Договор № 11 от 10.07.2026 по счету № 204 от 04.09.26 на сумму 10000-00 руб. Без налога (НДС) | K2: 46273 | L2: Семенов Владимир Александрович
A3: Оплата поставщикам Прочие поставщики 4121 | B3: 10000 | C3: АРКАДА ООО | D3: СИ00-036231 | E3: 15.09.2026 15:55:27 | F3: Согласована | G3: Сервис-Интегратор ООО | H3: ДТ НОВЫЙ УРЕНГОЙ | I3: Стандартный | J3: Оплата по Договор № 11 от 10.07.2026 по счету № 208 от 10.09.26 на сумму 10000-00 руб. Без налога (НДС) | K3: 46280 | L3: Семенов Владимир Александрович
A4: Оплата поставщикам Прочие поставщики 4121 | B4: 1020000 | C4: МОРОЗОФФ ООО | D4: СИ00-036229 | E4: 15.09.2026 15:21:55 | F4: Согласована | G4: Сервис-Интегратор ООО | H4: ДТ УК | I4: Стандартный | J4: Оплата 30% по Договору поставки № 1641/2026 от 01.09.2026 (подарки на НГ) на сумму 1020000-00 руб. В т.ч. НДС (22%) 183934-43 руб. | K4: 46282 | L4: Тохташева Ирина Анатольевна
A5: Оплата поставщикам Прочие поставщики 4121 | B5: 65736 | C5: МОСКОВСКИЙ МЕТРОПОЛИТЕН ГУП | D5: СИ00-036232 | E5: 15.09.2026 16:03:58 | F5: Согласована | G5: Сервис-Интегратор ООО | H5: ДТ УК | I5: Стандартный | J5: Оплата по Договор № 5398м на оказание услуг по обучению от 03.09.2025 по счету на сумму 65736-00 руб. В т.ч. НДС (22%) 11854-03 руб. | K5: 46280 | L5: Семенов Владимир Александрович
A6: Оплата поставщикам Прочие поставщики 4121 | B6: 123200 | C6: Мультибрендовый ООО | D6: СИ00-035959 | E6: 14.09.2026 14:18:40 | F6: Согласована | G6: Сервис-Интегратор ООО | H6: ДТ КАЗАНЬ | I6: Стандартный | J6: Оплата по Спецификации №14 от 08.09.2026 к Договору № 20251031/3 от 31.10.2025 123200-00 руб. В т.ч. НДС (22%) 22216-39 руб. | K6: 46280 | L6: Даль Надежда Дмитриевна
A7: Оплата поставщикам Прочие поставщики 4121 | B7: 54180.2 | C7: РАДЕЖ ТЕХСЕРВИС ООО (до 24.12.2025 ФЭТС ООО) | D7: СИ00-036230 | E7: 15.09.2026 15:53:25 | F7: Согласована | G7: Сервис-Интегратор ООО | H7: ДТ УК | I7: Стандартный | J7: Оплата по акту №204 от 31.08.2026 на сумму 54180-20 руб. В т.ч. НДС (22%) 9770-20 руб. | K7: 46282 | L7: Тохташева Ирина Анатольевна
A8: Оплата поставщикам Шины 4121 | B8: 400000 | C8: САМ - МБ ООО (КПП 500101001) | D8: СИ00-035958 | E8: 13.08.2026 12:12:00 | F8: Согласована | G8: Сервис-Интегратор ООО | H8: ДТ КАЗАНЬ | I8: Стандартный | J8: Оплата по Спецификациям Договора поставки № 10/13/03-2017 от 13.10.2017 за шины для служебных ТС 400000-00 руб. В т.ч. НДС (22%) 72131-15 руб. | K8: 46276 | L8: Винокуров Роман Александрович
A9: Оплата поставщикам Прочие поставщики 4121 | B9: 6700 | C9: СТИВ СЕРВИС ООО | D9: СИ00-026922 | E9: 16.07.2026 17:53:56 | F9: Согласована | G9: Сервис-Интегратор ООО | H9: ДТ КУЮМБА | I9: Стандартный | J9: Оплата по Договору № С2-26 от 13.03.2026 на оказание услуг по техническому обслуживанию оргтехники 6700-00 руб. В т.ч. НДС (22%) 1208-19 руб. | K9: 46266 | L9: Даль Надежда Дмитриевна
A10: Оплата поставщикам Прочие поставщики 4121 | B10: 5100 | C10: СТИВ СЕРВИС ООО | D10: СИ00-031224 | E10: 13.08.2026 16:56:45 | F10: Согласована | G10: Сервис-Интегратор ООО | H10: ДТ КУЮМБА | I10: Стандартный | J10: Оплата по Договору № С2-26 от 13.03.2026 на оказание услуг по техническому обслуживанию оргтехники 5100-00 руб. В т.ч. НДС (22%) 919-67 руб. | K10: 46282 | L10: Даль Надежда Дмитриевна
A11: Оплата поставщикам Прочие поставщики 4121 | B11: 9000 | C11: ТМ-СЕРВИС ООО | D11: СИ00-030257 | E11: 09.08.2026 13:05:59 | F11: Согласована | G11: Сервис-Интегратор ООО | H11: ДТ БУРЯТИЯ | I11: Стандартный | J11: Право на использование и предоставление доступа к программе для ЭВМ "Медицинский терминал" за июль 2026г. по счету №525 от 31.07.2026 Бурятия Без НДС | K11: 46247 | L11: Фокин Андрей Владимирович
A12: Оплата поставщикам Прочие поставщики 4121 | B12: 9000 | C12: ТМ-СЕРВИС ООО | D12: СИ00-035621 | E12: 13.09.2026 9:24:22 | F12: Согласована | G12: Сервис-Интегратор ООО | H12: ДТ БУРЯТИЯ | I12: Стандартный | J12: Право на использование и предоставление доступа к программе для ЭВМ "Медицинский терминал" за август 2026г. по счету №599 от 31.08.2026 Бурятия Без НДС | K12: 46280 | L12: Фокин Андрей Владимирович
A13: Оплата поставщикам Прочие поставщики 4121 | B13: 6000 | C13: ТМ-СЕРВИС ООО | D13: СИ00-035622 | E13: 13.09.2026 9:27:12 | F13: Согласована | G13: Сервис-Интегратор ООО | H13: ДТ КАЗАНЬ | I13: Стандартный | J13: Право на использование и предоставление доступа к программе для ЭВМ "Медицинский терминал" за август 2026г. по счету №600 от 31.08,2026 Казань Без НДС | K13: 46280 | L13: Фокин Андрей Владимирович
... A19: Оплата поставщикам Прочие поставщики 4121 | B19: 303983.74 | C19: ТЭК-ТОРГ АО | D19: СИ00-036133 | E19: 15.09.2026 9:34:53 | F19: Согласована | G19: Сервис-Интегратор ООО | H19: ДТ УК | I19: Стандартный | J19: Оплата по Основной договор УК 303983-74 руб. В т.ч. НДС (22%) 54816-74 руб. Пополнение лицевого счета №1100050800/1. Годовой тариф для участия в тендерах. | K19: 46294 | L19: Смирнов Владимир Сергеевич
A24: Сводная таблица оплат по подразделениям
A26: Контрагент | B26: ДТ БУРЯТИЯ | C26: ДТ КАЗАНЬ | D26: ДТ КУЗБАСС | E26: ДТ КУЮМБА | F26: ДТ НОВЫЙ УРЕНГОЙ | G26: ДТ ТОБОЛЬСК | H26: ДТ УК | I26: Итого | J26: Пояснение
A27: АРКАДА ООО | B27: 0 | C27: 0 | D27: 0 | E27: 0 | F27: 20000 | G27: 0 | H27: 0 | I27: 20000 | J27: Медосмотры
A28: МОРОЗОФФ ООО | B28: 0 | C28: 0 | D28: 0 | E28: 0 | F28: 0 | G28: 0 | H28: 1020000 | I28: 1020000 | J28: Конфеты и подарки
A29: МОСКОВСКИЙ МЕТРОПОЛИТЕН ГУП | B29: 0 | C29: 0 | D29: 0 | E29: 0 | F29: 0 | G29: 0 | H29: 65736 | I29: 65736 | J29: Обучение
A30: Мультибрендовый ООО | B30: 0 | C30: 123200 | D30: 0 | E30: 0 | F30: 0 | G30: 0 | H30: 0 | I30: 123200 | J30: Расходы IT
A31: РАДЕЖ ТЕХСЕРВИС ООО (до 24.12.2025 ФЭТС ООО) | B31: 0 | C31: 0 | D31: 0 | E31: 0 | F31: 0 | G31: 0 | H31: 54180.2 | I31: 54180.2 | J31: ТО пожарной сигнализации
A32: САМ - МБ ООО (КПП 500101001) | B32: 0 | C32: 400000 | D32: 0 | E32: 0 | F32: 0 | G32: 0 | H32: 0 | I32: 400000 | J32: Шины
A33: СТИВ СЕРВИС ООО | B33: 0 | C33: 0 | D33: 0 | E33: 11800 | F33: 0 | G33: 0 | H33: 0 | I33: 11800 | J33: Обслуживание оргтехники
A34: ТМ-СЕРВИС ООО | B34: 18000 | C34: 6000 | D34: 21000 | E34: 6000 | F34: 0 | G34: 21000 | H34: 0 | I34: 72000 | J34: Телемедики
A35: ТЭК-ТОРГ АО | B35: 0 | C35: 0 | D35: 0 | E35: 0 | F35: 0 | G35: 0 | H35: 303983.74 | I35: 303983.74 | J35: Тендеры
A36: ИТОГО | B36: 18000 | C36: 529200 | D36: 21000 | E36: 17800 | F36: 20000 | G36: 21000 | H36: 1443899.9 | I36: 2070899.9

Sheet Жилье, питание, связь, аренда
A1: Статья движения денежных средств | B1: Сумма | C1: Получатель | D1: Заявка | E1: Дата заявки | F1: Статус | G1: Организация | H1: Подразделение | I1: Приоритет | J1: Назначение платежа | K1: Дата оплаты | L1: Заявитель
A2: Оплата поставщикам Аренда помещений, коммунальные платежи и связь 4121 | B2: 25000 | C2: Алексеев Владимир Анатольевич | D2: СИ00-034619 | E2: 07.09.2026 6:49:40 | F2: Согласована | G2: Сервис-Интегратор ООО | H2: ДТ КУЗБАСС | I2: Стандартный | J2: Оплата по Договор Аренды жилого помещения б/н от 01.04.24 г. за СЕНТЯБРЬ 2026. Сумма 25000-00 руб. Без налога (НДС) | K2: 46280 | L2: Мерзлякова Линара Фаритовна
A3: Оплата поставщикам Аренда помещений, коммунальные платежи и связь 4121 | B3: 58000 | C3: БРИЗ ООО (ИНН 5401336141) | D3: СИ00-036077 | E3: 15.09.2026 7:44:53 | F3: Согласована | G3: Сервис-Интегратор ООО | H3: ДТ УК | I3: Стандартный | J3: Оплата арендной платы за 10/26 г. 58000-00 руб. В т.ч. НДС (5%) 2761-90 руб. | K3: 46281 | L3: Моисеева Юлия Анатольевна
A4: Оплата поставщикам Питание 4121 | B4: 8252 | C4: ВЕГА ООО (ИНН 2461046522) | D4: СИ00-035109 | E4: 09.09.2026 22:00:38 | F4: Согласована | G4: Сервис-Интегратор ООО | H4: ДТ КУЮМБА | I4: Стандартный | J4: Оплата по договору № от 01.09.2023 8252-00 без налога (НДС), Оплата за питание 110 куст УПД № 811 от 31.08.2026. | K4: 46280 | L4: Калинина Валерия Владимировна
A5: Оплата поставщикам Аренда помещений, коммунальные платежи и связь 4121 | B5: 71332.06 | C5: ВЫМПЕЛКОМ ПАО (КПП 771301001) | D5: СИ00-036233 | E5: 15.09.2026 16:05:07 | F5: Согласована | G5: Сервис-Интегратор ООО | H5: ДТ УК | I5: Стандартный | J5: Оплата за услуги связи по Договору № 374760482 за август 2026. В т.ч. НДС (22%) 12863-16 руб. | K5: 46282 | L5: Даль Надежда Дмитриевна
A6: Оплата поставщикам Аренда помещений, коммунальные платежи и связь 4121 | B6: 40000 | C6: Гордейко Янина Викторовна | D6: СИ00-036036 | E6: 15.09.2026 6:18:07 | F6: Согласована | G6: Сервис-Интегратор ООО | H6: ДТ КУЮМБА | I6: Стандартный | J6: Оплата по Договор аренды от 09.04.2024 40000-00 руб. Без налога (НДС) | K6: 46282 | L6: Елизарова Екатерина Александровна
A7: Оплата поставщикам Аренда помещений, коммунальные платежи и связь 4121 | B7: 3720 | C7: Е-Лайт-Телеком ООО | D7: СИ00-035103 | E7: 09.09.2026 22:00:03 | F7: Согласована | G7: Сервис-Интегратор ООО | H7: ДТ КУЗБАСС | I7: Стандартный | J7: Оплата по договору №10362-ю от 26.05.2015 за услуги Интернет за Август 3720-00 В т.ч. НДС (22%) 670-82 руб. | K7: 46280 | L7: Шульгин Андрей Павлович
A8: Оплата поставщикам Аренда помещений, коммунальные платежи и связь 4121 | B8: 613.07 | C8: КУЗБАССЭНЕРГОСБЫТ ПАО КПП 775050001 | D8: СИ00-035632 | E8: 14.09.2026 3:21:19 | F8: Согласована | G8: Сервис-Интегратор ООО | H8: ДТ КУЗБАСС | I8: Стандартный | J8: Оплата по Договор № 710870 энергоснабжения от 18.10.2024 613-07 руб.окончательный платеж за август 26г. В т.ч. НДС (22%) 110-55 руб. | K8: 46280 | L8: Титова Наталья Викторовна
A9: Оплата поставщикам Аренда помещений, коммунальные платежи и связь 4121 | B9: 1462 | C9: КУЗБАССЭНЕРГОСБЫТ ПАО КПП 775050001 | D9: СИ00-035633 | E9: 14.09.2026 3:27:56 | F9: Согласована | G9: Сервис-Интегратор ООО | H9: ДТ КУЗБАСС | I9: Стандартный | J9: Оплата по Договор № 710870 энергоснабжения от 18.10.2024 1462-00 руб. промежуточный плате за сентябрь 26 г. В т.ч. НДС (22%) 263-64 руб. | K9: 46280 | L9: Титова Наталья Викторовна
A10: Оплата поставщикам Аренда помещений, коммунальные платежи и связь 4121 | B10: 18458.6 | C10: МЕГАФОН ПАО (КПП 667003001) | D10: СИ00-034660 | E10: 07.09.2026 8:07:47 | F10: Согласована | G10: Сервис-Интегратор ООО | H10: ДТ ТОБОЛЬСК | I10: Стандартный | J10: Оплата по Договор об оказании услуг связи № ФД-СтФ-1687/2020 от 06.05.2020 (л/с 735012451) 18458-60 руб. В т.ч. НДС (22%) 3328-60 руб. | K10: 46280 | L10: Силин Никита Сергеевич
A11: Оплата поставщикам Аренда помещений, коммунальные платежи и связь 4121 | B11: 231768.3 | C11: МТС ПАО (КПП 997750001) | D11: СИ00-036238 | E11: 15.09.2026 16:59:57 | F11: Согласована | G11: Сервис-Интегратор ООО | H11: ДТ УК | I11: Стандартный | J11: Оплата за услуги связи по единому л/с 277708098243 за июль 2026. В т.ч. НДС (22%) 41794-28 руб. | K11: 46282 | L11: Даль Надежда Дмитриевна
A12: Оплата поставщикам Аренда помещений, коммунальные платежи и связь 4121 | B12: 122096.77 | C12: МТС ПАО (КПП 997750001) | D12: СИ00-036239 | E12: 15.09.2026 17:03:29 | F12: Согласована | G12: Сервис-Интегратор ООО | H12: ДТ УК | I12: Стандартный | J12: Оплата за услуги связи по единому л/с 277757860774 за июль 2026. В т.ч. НДС (22%) 22017-45 руб. | K12: 46282 | L12: Даль Надежда Дмитриевна
A13: Оплата поставщикам Аренда помещений, коммунальные платежи и связь 4121 | B13: 10858 | C13: МУС ЭНЕРГЕТИКИ АО | D13: СИ00-034929 | E13: 08.09.2026 15:32:43 | F13: Согласована | G13: Сервис-Интегратор ООО | H13: ДТ БУРЯТИЯ | I13: Стандартный | J13: Оплата за услуги связи по Договору № ИН-15-04 от 08.07.2015 10858-00 руб. В т.ч. НДС (22%) 1958-00 руб. | K13: 46275 | L13: Даль Надежда Дмитриевна
... A36: Оплата поставщикам Прочие поставщики 4121 | B36: 131871 | C36: МТС РЕКЛАМНЫЕ ТЕХНОЛОГИИ АО | D36: СИ00-036237 | E36: 15.09.2026 16:55:58 | F36: Согласована | G36: Сервис-Интегратор ООО | H36: ДТ УК | I36: Стандартный | J36: Оплата за услуги связи по л/с 277780811169 за июль 2026. В т.ч. НДС (22%) 23780-02 руб. | K36: 46293 | L36: Даль Надежда Дмитриевна
A40: Сводная таблица оплат по подразделениям
A42: Контрагент | B42: ДТ БЕЛОГОРСК | C42: ДТ БУРЯТИЯ | D42: ДТ КАЗАНЬ | E42: ДТ КУЗБАСС | F42: ДТ КУЮМБА | G42: ДТ МОСКВА | H42: ДТ МУРМАНСК | I42: ДТ НОВЫЙ УРЕНГОЙ | J42: ДТ ОМСК | K42: ДТ ТОБОЛЬСК | L42: ДТ ТУРУХАНСК | M42: ДТ УК | N42: ДТ ХАКАСИЯ | O42: Итого | P42: Пояснение
A43: Алексеев Владимир Анатольевич | B43: 0 | C43: 0 | D43: 0 | E43: 25000 | F43: 0 | G43: 0 | H43: 0 | I43: 0 | J43: 0 | K43: 0 | L43: 0 | M43: 0 | N43: 0 | O43: 25000 | P43: Аренда
A44: БРИЗ ООО (ИНН 5401336141) | B44: 0 | C44: 0 | D44: 0 | E44: 0 | F44: 0 | G44: 0 | H44: 0 | I44: 0 | J44: 0 | K44: 0 | L44: 0 | M44: 58000 | N44: 0 | O44: 58000 | P44: Аренда
A45: ВЕГА ООО (ИНН 2461046522) | B45: 0 | C45: 0 | D45: 0 | E45: 0 | F45: 8252 | G45: 0 | H45: 0 | I45: 0 | J45: 0 | K45: 0 | L45: 0 | M45: 0 | N45: 0 | O45: 8252 | P45: Питание
A46: ВЫМПЕЛКОМ ПАО (КПП 771301001) | B46: 0 | C46: 0 | D46: 0 | E46: 0 | F46: 0 | G46: 0 | H46: 0 | I46: 0 | J46: 0 | K46: 0 | L46: 0 | M46: 71332.06 | N46: 0 | O46: 71332.06 | P46: Связь
A47: Гордейко Янина Викторовна | B47: 0 | C47: 0 | D47: 0 | E47: 0 | F47: 40000 | G47: 0 | H47: 0 | I47: 0 | J47: 0 | K47: 0 | L47: 0 | M47: 0 | N47: 0 | O47: 40000 | P47: Аренда
A48: Е-Лайт-Телеком ООО | B48: 0 | C48: 0 | D48: 0 | E48: 3720 | F48: 0 | G48: 0 | H48: 0 | I48: 0 | J48: 0 | K48: 0 | L48: 0 | M48: 0 | N48: 0 | O48: 3720 | P48: Связь
A49: КУЗБАССЭНЕРГОСБЫТ ПАО КПП 775050001 | B49: 0 | C49: 0 | D49: 0 | E49: 2075.07 | F49: 0 | G49: 0 | H49: 0 | I49: 0 | J49: 0 | K49: 0 | L49: 0 | M49: 0 | N49: 0 | O49: 2075.07 | P49: Коммуналка
A50: МЕГАФОН ПАО (КПП 667003001) | B50: 0 | C50: 0 | D50: 0 | E50: 0 | F50: 0 | G50: 0 | H50: 0 | I50: 0 | J50: 0 | K50: 18458.6 | L50: 0 | M50: 0 | N50: 0 | O50: 18458.6 | P50: Связь
A51: МТС ПАО (КПП 997750001) | B51: 0 | C51: 0 | D51: 0 | E51: 0 | F51: 0 | G51: 0 | H51: 0 | I51: 0 | J51: 0 | K51: 0 | L51: 0 | M51: 353865.07 | N51: 0 | O51: 353865.07 | P51: Связь
A52: МТС РЕКЛАМНЫЕ ТЕХНОЛОГИИ АО | B52: 0 | C52: 0 | D52: 0 | E52: 0 | F52: 0 | G52: 0 | H52: 0 | I52: 0 | J52: 0 | K52: 0 | L52: 0 | M52: 131871 | N52: 0 | O52: 131871 | P52: Связь
A53: МУС ЭНЕРГЕТИКИ АО | B53: 0 | C53: 10858 | D53: 0 | E53: 0 | F53: 0 | G53: 0 | H53: 0 | I53: 0 | J53: 0 | K53: 0 | L53: 0 | M53: 0 | N53: 0 | O53: 10858 | P53: Связь
A54: НЕОТРАНС- ХАКАСИЯ ООО | B54: 0 | C54: 0 | D54: 0 | E54: 0 | F54: 0 | G54: 0 | H54: 0 | I54: 0 | J54: 0 | K54: 0 | L54: 0 | M54: 0 | N54: 127776 | O54: 127776 | P54: Субаренда гаража
... A73: ЭР-ТЕЛЕКОМ МОСКВА ООО | B73: 0 | C73: 0 | D73: 0 | E73: 0 | F73: 0 | G73: 7990.35 | H73: 0 | I73: 0 | J73: 0 | K73: 0 | L73: 0 | M73: 0 | N73: 0 | O73: 7990.35 | P73: Связь
A74: ИТОГО | B74: 150968 | C74: 21011.09 | D74: 27799.05 | E74: 288095.98 | F74: 98252 | G74: 7990.35 | H74: 225000 | I74: 780 | J74: 300 | K74: 60125.6 | L74: 1493535 | M74: 1029417.7 | N74: 129847.26 | O74: 3533122

Sheet Непереносимые оплаты
A1: Статья движения денежных средств | B1: Сумма | C1: Получатель | D1: Заявка | E1: Дата заявки | F1: Статус | G1: Организация | H1: Подразделение | I1: Приоритет | J1: Назначение платежа | K1: Дата оплаты | L1: Заявитель
A2: Оплата масел и иных смазочных материалов 4121 | B2: 112331.01 | C2: ГАЗПРОМНЕФТЬ -СМ ООО | D2: СИ00-029626 | E2: 05.08.2026 6:15:16 | F2: Согласована | G2: Сервис-Интегратор ООО | H2: ДТ КАЗАНЬ | I2: Стандартный | J2: Оплата по накладной №СМ-29315 от 21.07.2026 112331-01 руб. В т.ч. НДС (22%) 20256-41 руб. | K2: 46282 | L2: Ванюкевич Лилия Владимировна
A3: Оплата масел и иных смазочных материалов 4121 | B3: 130354 | C3: ГАЗПРОМНЕФТЬ -СМ ООО | D3: СИ00-029623 | E3: 05.08.2026 6:03:43 | F3: Согласована | G3: Сервис-Интегратор ООО | H3: ДТ КУЗБАСС | I3: Стандартный | J3: Оплата по накладной №СМ-28846 от 19.07.2026 130354-00 руб. В т.ч. НДС (22%) 23506-46 руб. | K3: 46282 | L3: Ванюкевич Лилия Владимировна
A4: Оплата поставщикам Аренда помещений, коммунальные платежи и связь 4121 | B4: 7840.5 | C4: ЭКОТЕК ООО | D4: СИ00-035276 | E4: 10.09.2026 22:00:15 | F4: Согласована | G4: Сервис-Интегратор ООО | H4: ДТ КУЗБАСС | I4: Стандартный | J4: Оплата по договору №172100-2024/ТКО от 25.10.2024 7840-50 руб. услуга по обращению с ТКО август 26г. Без налога (НДС) | K4: 46281 | L4: Титова Наталья Викторовна
A5: Оплата поставщикам Аренда ТС 4121 | B5: 117340.34 | C5: Славнефть-Красноярскнефтегаз ООО ОП Куюмба | D5: СИ00-036046 | E5: 15.09.2026 8:00:00 | F5: Согласована | G5: Сервис-Интегратор ООО | H5: ДТ КУЮМБА | I5: Стандартный | J5: Оплата по Договор аренды движимого имущества № В044024/0864Д от 01.09.2024 117340-34 руб. В т.ч. НДС (22%) 21159-73 руб. | K5: 46282 | L5: Родина Анна Владимировна
A6: Оплата масел и иных смазочных материалов 4121 | B6: 119458.01 | C6: ГАЗПРОМНЕФТЬ -СМ ООО | D6: СИ00-029625 | E6: 05.08.2026 6:13:37 | F6: Согласована | G6: Сервис-Интегратор ООО | H6: ДТ МУРМАНСК | I6: Стандартный | J6: Оплата по накладной №СМ-28463 от 13.07.2026 119458-01 руб. В т.ч. НДС (22%) 21541-61 руб. | K6: 46282 | L6: Ванюкевич Лилия Владимировна
A7: Оплата поставщикам Прочие поставщики 4121 | B7: 1318.18 | C7: Дальневосточная энергетическая компания ПАО (КПП 997650001) | D7: СИ00-036260 | E7: 16.09.2026 2:55:34 | F7: Согласована | G7: Сервис-Интегратор ООО | H7: ДТ СВОБОДНЫЙ | I7: Стандартный | J7: Оплата по Договор электроснабжения № СВООЭ0000405 от 21.04.2022 1318-18 руб. В т.ч. НДС (20%) 219-70 руб. | K7: 46281 | L7: Перфильева Екатерина Николаевна
A8: Оплата масел и иных смазочных материалов 4121 | B8: 253665.06 | C8: ГАЗПРОМНЕФТЬ -СМ ООО | D8: СИ00-029622 | E8: 05.08.2026 5:59:09 | F8: Согласована | G8: Сервис-Интегратор ООО | H8: ДТ ТОБОЛЬСК | I8: Стандартный | J8: Оплата по накладной №СМ-28826 от 17.07.2026 253665-06 руб. В т.ч. НДС (22%) 45742-88 руб. | K8: 46282 | L8: Ванюкевич Лилия Владимировна
A13: Сводная таблица оплат по подразделениям
A15: Контрагент | B15: ДТ КАЗАНЬ | C15: ДТ КУЗБАСС | D15: ДТ КУЮМБА | E15: ДТ МУРМАНСК | F15: ДТ СВОБОДНЫЙ | G15: ДТ ТОБОЛЬСК | H15: Итого | I15: Пояснение
A16: ГАЗПРОМНЕФТЬ -СМ ООО | B16: 112331.01 | C16: 130354 | D16: 0 | E16: 119458.01 | F16: 0 | G16: 253665.06 | H16: 615808.08 | I16: Масла - (Непереносимые оплаты)
A17: Дальневосточная энергетическая компания ПАО (КПП 997650001) | B17: 0 | C17: 0 | D17: 0 | E17: 0 | F17: 1318.18 | G17: 0 | H17: 1318.18 | I17: Аренда
A18: Славнефть-Красноярскнефтегаз ООО ОП Куюмба | B18: 0 | C18: 0 | D18: 117340.34 | E18: 0 | F18: 0 | G18: 0 | H18: 117340.34 | I18: Перелеты
A19: ЭКОТЕК ООО | B19: 0 | C19: 7840.5 | D19: 0 | E19: 0 | F19: 0 | G19: 0 | H19: 7840.5 | I19: Обращение с ТКО
A20: ИТОГО | B20: 112331.01 | C20: 138194.5 | D20: 117340.34 | E20: 119458.01 | F20: 1318.18 | G20: 253665.06 | H20: 742307.1

Sheet Оплаты в рамках 100 т.р.
A1: Статья движения денежных средств | B1: Сумма | C1: Получатель | D1: Заявка | E1: Дата заявки | F1: Статус | G1: Организация | H1: Подразделение | I1: Приоритет | J1: Назначение платежа | K1: Дата оплаты | L1: Заявитель
A2: Оплата поставщикам Аренда помещений, коммунальные платежи и связь 4121 | B2: 50715 | C2: Снидко Артём Андреевич ИП | D2: СИ00-034778 | E2: 08.09.2026 8:06:05 | F2: Согласована | G2: Сервис-Интегратор ООО | H2: ДТ ТОБОЛЬСК | I2: Стандартный | J2: Оплата по накладной №сд00007660 от 31.08.2026 50715-00 руб. Оплата парковки служебных ТС за август 2026г. В т.ч. НДС (5%) 2415-00 руб. | K2: 46274 | L2: Надеина Любовь Валентиновна
A3: Оплата поставщикам Прочие поставщики 4121 | B3: 7325 | C3: ИНСТРУМЕНТ-ЦЕНТР ООО | D3: СИ00-033220 | E3: 27.08.2026 12:53:50 | F3: Согласована | G3: Сервис-Интегратор ООО | H3: ДТ ТОБОЛЬСК | I3: Стандартный | J3: Оплата по накладной №ТН-5439 от 18.08.2026 4655-00 руб., накладной №ТН-5444 от 18.08.2026 2670-00 руб. В т.ч. НДС (22%) 1320-91 руб.Материалы д/гаражной службы. | K3: 46267 | L3: Калачинская Надежда Ивановна
A4: Оплата поставщикам Аренда помещений, коммунальные платежи и связь 4121 | B4: 7000 | C4: ЮГОР АО | D4: СИ00-034385 | E4: 04.09.2026 7:11:09 | F4: Согласована | G4: Сервис-Интегратор ООО | H4: ДТ ТОБОЛЬСК | I4: Стандартный | J4: Оплата по накладной №3417 от 31.08.2026 7000-00 руб. Оплата аренды парковочных мест служебных ТС за август 2026г. В т.ч. НДС (22%) 1262-30 руб. | K4: 46275 | L4: Надеина Любовь Валентиновна
A5: Оплата поставщикам Прочие поставщики 4121 | B5: 34414 | C5: ИНСТРУМЕНТ-ЦЕНТР ООО | D5: СИ00-033221 | E5: 27.08.2026 12:55:31 | F5: Согласована | G5: Сервис-Интегратор ООО | H5: ДТ ТОБОЛЬСК | I5: Стандартный | J5: Оплата по накладной №ТН-5594 от 26.08.2026 34414-00 руб. В т.ч. НДС (22%) 6205-81 руб.Материалы д/гаражной сл. | K5: 46274 | L5: Калачинская Надежда Ивановна
A6: Оплата поставщикам Запчасти, ремонт 4121 | B6: 17885.2 | C6: ЛОГИКА - СЕРВИС ООО | D6: СИ00-035342 | E6: 11.09.2026 5:52:35 | F6: Согласована | G6: Сервис-Интегратор ООО | H6: ДТ ТУРУХАНСК | I6: Стандартный | J6: Оплата по Оплата по Спецификациям Договора №16/П/2013/С-И от 02.10.2013г ТУР(СИ) 17885-20 руб. В т.ч. НДС (22%) 3225-20 руб. 9878 №М749МВ797 ТПУ | K6: 46276 | L6: Кокоулин Дмитрий Геннадьевич
A7: Оплата поставщикам Запчасти, ремонт 4121 | B7: 18047.46 | C7: СибНовоТех ООО | D7: СИ00-031885 | E7: 19.08.2026 5:07:13 | F7: Согласована | G7: Сервис-Интегратор ООО | H7: ДТ ТУРУХАНСК | I7: Стандартный | J7: Оплата по Оплата по Спецификациям Договора поставки № 1143-18 от 18.10.2018 18047-46 руб. В т.ч. НДС (22%) 3254-46 руб. 8750 ТС: демонтаж с Р905АО797 на С436ЕТ797 АК3 ВПУ | K7: 46253 | L7: Антипкин Вадим Викторович
A8: Оплата поставщикам Запчасти, ремонт 4121 | B8: 11648.32 | C8: СибНовоТех ООО | D8: СИ00-030919 | E8: 12.08.2026 13:25:38 | F8: Согласована | G8: Сервис-Интегратор ООО | H8: ДТ ТУРУХАНСК | I8: Стандартный | J8: Оплата по Оплата по Спецификациям Договора поставки № 1143-18 от 18.10.2018 11648-32 руб. В т.ч. НДС (22%) 2100-52 руб. 8821 №С950АУ ТПУ | K8: 46246 | L8: Кокоулин Дмитрий Геннадьевич
A13: Сводная таблица оплат по подразделениям
A15: Контрагент | B15: ДТ ТОБОЛЬСК | C15: ДТ ТУРУХАНСК | D15: Итого | E15: Пояснение
A16: ИНСТРУМЕНТ-ЦЕНТР ООО | B16: 41739 | C16: 0 | D16: 41739 | E16: ТМЦ
A17: ЛОГИКА - СЕРВИС ООО | B17: 0 | C17: 17885.2 | D17: 17885.2 | E17: Запчасти
A18: СибНовоТех ООО | B18: 0 | C18: 29695.78 | D18: 29695.78 | E18: Запчасти
A19: Снидко Артём Андреевич ИП | B19: 50715 | C19: 0 | D19: 50715 | E19: Парковка
A20: ЮГОР АО | B20: 7000 | C20: 0 | D20: 7000 | E20: Парковка
A21: ИТОГО | B21: 99454 | C21: 47580.98 | D21: 147034.98

Sheet График
A1: Статья движения денежных средств | B1: Сумма | C1: Получатель | D1: Заявка | E1: Дата заявки | F1: Статус | G1: Организация | H1: Подразделение | I1: Приоритет | J1: Назначение платежа | K1: Дата оплаты | L1: Заявитель
A2: Оплата поставщикам Запчасти, ремонт 4121 | B2: 58950 | C2: АВТОСКЛАД ООО | D2: СИ00-016058 | E2: 30.04.2026 22:00:37 | F2: Согласована | G2: Сервис-Интегратор ООО | H2: ДТ ЭЛЬГА | I2: Стандартный | J2: Оплата по договору №СИ (Отсрочка 15 дней) от 22.08.2023 58950-00 В т.ч. НДС (22%) 10630-33 руб. | K2: 46148 | L2: Мамаев Валерий Николаевич
A3: Оплата поставщикам Запчасти, ремонт 4121 | B3: 128600 | C3: АВТОСКЛАД ООО | D3: СИ00-018214 | E3: 16.05.2026 22:00:13 | F3: Согласована | G3: Сервис-Интегратор ООО | H3: ДТ ЭЛЬГА | I3: Стандартный | J3: Оплата по договору №СИ (Отсрочка 15 дней) от 22.08.2023 128600-00 В т.ч. НДС (22%) 23190-15 руб. | K3: 46164 | L3: Мамаев Валерий Николаевич
A4: Оплата поставщикам Запчасти, ремонт 4121 | B4: 212450 | C4: АВТОСКЛАД ООО | D4: СИ00-021350 | E4: 09.06.2026 22:00:05 | F4: Согласована | G4: Сервис-Интегратор ООО | H4: ДТ ЭЛЬГА | I4: Стандартный | J4: Оплата по договору №СИ (Отсрочка 15 дней) от 22.08.2023 303500-00 В т.ч. НДС (22%) 54729-51 руб. | K4: 46188 | L4: Мамаев Валерий Николаевич
A5: Оплата поставщикам Прочие поставщики 4121 | B5: 1026 | C5: АВТО-ТРЕЙД ООО | D5: СИ00-026548 | E5: 09.07.2026 8:40:03 | F5: Согласована | G5: Сервис-Интегратор ООО | H5: ДТ АПАТИТЫ | I5: Стандартный | J5: Оплата по Договору № 2021/ОРГ-12345 поставки товаров (зап.части) от 27.05.2021 УПД № 990/5 от 09.07.2026 1026-00 руб.в т.ч. НДС (22%) 185,02 руб. | K5: 46257 | L5: Базанова Вера Анатольевна
A6: Оплата поставщикам Прочие поставщики 4121 | B6: 17088 | C6: АВТО-ТРЕЙД ООО | D6: СИ00-027062 | E6: 15.07.2026 23:59:59 | F6: Согласована | G6: Сервис-Интегратор ООО | H6: ДТ МУРМАНСК | I6: Стандартный | J6: Оплата за приобретение запчастей для ТС по накладной № 9081 от 15.07.2026 17088-00 руб.в т. ч. НДС 3081-44 руб. | K6: 46261 | L6: Шульга Алёна Владимировна
A7: Оплата поставщикам Прочие поставщики 4121 | B7: 14851 | C7: АВТО-ТРЕЙД ООО | D7: СИ00-027063 | E7: 15.07.2026 23:59:59 | F7: Согласована | G7: Сервис-Интегратор ООО | H7: ДТ МУРМАНСК | I7: Стандартный | J7: Оплата за приобретение запчастей для ТС по накладной № 9082 от 15.07.2026 14851-00 руб.в т. ч. НДС 2678-05 руб. | K7: 46261 | L7: Шульга Алёна Владимировна
A8: Оплата поставщикам Прочие поставщики 4121 | B8: 3840 | C8: АВТО-ТРЕЙД ООО | D8: СИ00-027583 | E8: 22.07.2026 17:06:29 | F8: Согласована | G8: Сервис-Интегратор ООО | H8: ДТ АПАТИТЫ | I8: Стандартный | J8: Оплата за приобретение запчастей для ТС по накладной № 994/5 от 14.07.2026 3840-00 руб.в т. ч. НДС 692-46 руб. | K8: 46262 | L8: Базанова Вера Анатольевна
A9: Оплата поставщикам Прочие поставщики 4121 | B9: 22218 | C9: АВТО-ТРЕЙД ООО | D9: СИ00-029521 | E9: 04.08.2026 13:40:16 | F9: Согласована | G9: Сервис-Интегратор ООО | H9: ДТ АПАТИТЫ | I9: Стандартный | J9: Оплата за приобретение запчастей для ТС по накладной № 996/5 от 15.07.2026 22218-00 руб.в т. ч. НДС 4006-53 руб. | K9: 46263 | L9: Базанова Вера Анатольевна
A10: Оплата поставщикам Прочие поставщики 4121 | B10: 6995 | C10: АВТО-ТРЕЙД ООО | D10: СИ00-026649 | E10: 15.07.2026 12:19:33 | F10: Согласована | G10: Сервис-Интегратор ООО | H10: ДТ АПАТИТЫ | I10: Стандартный | J10: Оплата по Договору № 2021/ОРГ-12345 поставки товаров (зап.части) от 27.05.2021 УПД № 995/5 от 15.07.2026 6695-00 руб.в т.ч. НДС (22%) 1261,39 руб. | K10: 46263 | L10: Базанова Вера Анатольевна
A11: Оплата поставщикам Прочие поставщики 4121 | B11: 39830 | C11: АВТО-ТРЕЙД ООО | D11: СИ00-029524 | E11: 15.07.2026 13:59:01 | F11: Согласована | G11: Сервис-Интегратор ООО | H11: ДТ АПАТИТЫ | I11: Стандартный | J11: Оплата за приобретение запчастей для ТС по накладной №998/5 от 15.07.2026 39830-00 руб.в т. ч. НДС 7182-46 руб. | K11: 46263 | L11: Базанова Вера Анатольевна
A12: Оплата поставщикам Прочие поставщики 4121 | B12: 19490 | C12: АВТО-ТРЕЙД ООО | D12: СИ00-029359 | E12: 03.08.2026 15:41:32 | F12: Согласована | G12: Сервис-Интегратор ООО | H12: ДТ МУРМАНСК | I12: Стандартный | J12: Оплата за приобретение запчастей для ТС по накладной № 9195 от 03.08.2026 19490-00 руб.в т. ч. НДС 3514-59 руб. | K12: 46280 | L12: Шульга Алёна Владимировна
A13: Оплата поставщикам Прочие поставщики 4121 | B13: 13990 | C13: АВТО-ТРЕЙД ООО | D13: СИ00-030947 | E13: 12.08.2026 15:03:39 | F13: Согласована | G13: Сервис-Интегратор ООО | H13: ДТ МУРМАНСК | I13: Стандартный | J13: Оплата за приобретение запчастей для ТС по накладной № 9237 от 12.08.2026 13990-00 руб.в т. ч. НДС 2522-79 руб. | K13: 46289 | L13: Шульга Алёна Владимировна
... A49: Оплата поставщикам Прочие поставщики 4121 | B49: 54614.45 | C49: ЦЭР И АУДИТА ООО | D49: СИ00-019011 | E49: 22.05.2026 6:53:22 | F49: Согласована | G49: Сервис-Интегратор ООО | H49: ДТ ТУРУХАНСК | I49: Стандартный | J49: Оплата по договору ЦЭРиА/120-2025 от 21.11.2025 выполнение работ по I, II, III, VIII, IX, X и XI этапам договора, согласно УПД № 05-0057 от 21.05.2026 г. Окончательный расчет 54 614,50 НДС (5%) 2600,69. | K49: 46167 | L49: Крапивина Татьяна Александровна
A54: Сводная таблица оплат по подразделениям
A56: Контрагент | B56: ДТ АПАТИТЫ | C56: ДТ БУРЯТИЯ | D56: ДТ ЖЕЛЕЗНОГОРСК | E56: ДТ КУЗБАСС | F56: ДТ КУЮМБА | G56: ДТ МУРМАНСК | H56: ДТ ОМСК | I56: ДТ ТОБОЛЬСК | J56: ДТ ТОМСК | K56: ДТ ТУРУХАНСК | L56: ДТ УК | M56: ДТ ЭЛЬГА | N56: ДТ ЮГРА | O56: Итого | P56: Пояснение
A57: АВТО-ТРЕЙД ООО | B57: 73909 | C57: 0 | D57: 0 | E57: 0 | F57: 0 | G57: 225121.09 | H57: 0 | I57: 0 | J57: 0 | K57: 0 | L57: 0 | M57: 0 | N57: 0 | O57: 299030.09 | P57: Запчасти
A58: АВТОСКЛАД ООО | B58: 0 | C58: 0 | D58: 0 | E58: 0 | F58: 0 | G58: 0 | H58: 0 | I58: 0 | J58: 0 | K58: 0 | L58: 0 | M58: 400000 | N58: 0 | O58: 400000 | P58: Запчасти
A59: БЕРКУТ ООО ЧОО | B59: 0 | C59: 0 | D59: 0 | E59: 0 | F59: 0 | G59: 0 | H59: 0 | I59: 548238.72 | J59: 0 | K59: 0 | L59: 0 | M59: 0 | N59: 0 | O59: 548238.72 | P59: Охрана
A60: ДЕМИДОВ ООО | B60: 0 | C60: 0 | D60: 0 | E60: 0 | F60: 0 | G60: 0 | H60: 0 | I60: 0 | J60: 0 | K60: 0 | L60: 0 | M60: 225000 | N60: 0 | O60: 225000 | P60: Транспортная экспедиция
A61: Енисейское речное пароходство АО | B61: 0 | C61: 0 | D61: 0 | E61: 0 | F61: 0 | G61: 0 | H61: 0 | I61: 0 | J61: 0 | K61: 500000 | L61: 0 | M61: 0 | N61: 0 | O61: 500000 | P61: Перевозка грузов
A62: КАРАВАН ООО (ИНН 4632253300) | B62: 0 | C62: 0 | D62: 200000 | E62: 0 | F62: 0 | G62: 0 | H62: 0 | I62: 0 | J62: 0 | K62: 0 | L62: 0 | M62: 0 | N62: 0 | O62: 200000 | P62: Техосмотры
A63: КРАЕВОЙ УРАЛАВТОЦЕНТР ООО | B63: 0 | C63: 0 | D63: 0 | E63: 0 | F63: 22300 | G63: 0 | H63: 0 | I63: 0 | J63: 0 | K63: 12345 | L63: 0 | M63: 0 | N63: 0 | O63: 34645 | P63: Запчасти
A64: МАГЕЛАН ООО | B64: 0 | C64: 0 | D64: 0 | E64: 0 | F64: 0 | G64: 0 | H64: 0 | I64: 0 | J64: 0 | K64: 0 | L64: 0 | M64: 0 | N64: 382500 | O64: 382500 | P64: Оплата за аренду помещения за июнь 2026г. по счету № 303 от 01.06.2026г.(Дог. аренды № 01/08/2025 от 01.08.2025) 382 500-00 руб. Без налога НДС
A65: МСН ГРУП ГОРОДА МОСКВЫ АБ | B65: 0 | C65: 0 | D65: 0 | E65: 0 | F65: 0 | G65: 0 | H65: 0 | I65: 0 | J65: 0 | K65: 0 | L65: 250000 | M65: 0 | N65: 0 | O65: 250000 | P65: Аудиторы
A66: ОЦ ВИТАЛЕНА ООО | B66: 0 | C66: 0 | D66: 0 | E66: 0 | F66: 329650 | G66: 0 | H66: 0 | I66: 0 | J66: 0 | K66: 0 | L66: 0 | M66: 0 | N66: 0 | O66: 329650 | P66: Медосмотры
A67: Полевцов Александр Игоревич ИП | B67: 0 | C67: 0 | D67: 0 | E67: 132480 | F67: 0 | G67: 0 | H67: 0 | I67: 0 | J67: 0 | K67: 0 | L67: 0 | M67: 0 | N67: 0 | O67: 132480 | P67: Закупка ТМЦ
A68: СЕММИТ ООО | B68: 0 | C68: 0 | D68: 0 | E68: 189045.9 | F68: 0 | G68: 0 | H68: 0 | I68: 0 | J68: 0 | K68: 0 | L68: 0 | M68: 0 | N68: 0 | O68: 189045.9 | P68: Запчасти
... A75: ЦЭР И АУДИТА ООО | B75: 0 | C75: 0 | D75: 0 | E75: 0 | F75: 0 | G75: 0 | H75: 0 | I75: 0 | J75: 0 | K75: 54614.45 | L75: 0 | M75: 0 | N75: 0 | O75: 54614.45 | P75: Выполнение работ по разработке и согласованию проектной документации
A76: ИТОГО | B76: 73909 | C76: 282882.18 | D76: 200000 | E76: 423075.9 | F76: 943205.97 | G76: 225121.09 | H76: 4600 | I76: 678278.72 | J76: 20015 | K76: 776959.45 | L76: 250000 | M76: 625000 | N76: 382500 | O76: 4885547.3

Sheet Согласовано
A1: Статья движения денежных средств | B1: Сумма | C1: Получатель | D1: Заявка | E1: Дата заявки | F1: Статус | G1: Организация | H1: Подразделение | I1: Приоритет | J1: Назначение платежа | K1: Дата оплаты | L1: Заявитель
A2: Оплата за государственные пошлины, штрафы, исполнительные производства 4129 | B2: 1000000 | C2: УФК по Нижегородской области (Павловское РОСП ГУ ФССП по Нижегородской области, л/с 05321845290) | D2: СИ00-036432 | E2: 16.09.2026 10:53:45 | F2: Согласована | G2: Сервис-Интегратор ООО | H2: ДТ ТУРУХАНСК | I2: Стандартный | J2: Оплата по постановлению об обращении взыскания на дебиторскую задолженность от 16.06.2026 в рамках испол.производства 28340/26/52040-ИП от 21.01.2026 в отношении ООО"СОЮЗ-ЭНЕРГО"/УИН32252040260028340006 | K2: 46325 | L2: Миненков Андрей Юрьевич
A3: Оплата поставщикам Перелеты и тревел-поставщики 4121 | B3: 516000 | C3: РАТЕЛ АВИАСЕРВИС ООО | D3: СИ00-027739 | E3: 24.07.2026 5:51:27 | F3: Согласована | G3: Сервис-Интегратор ООО | H3: ДТ ЭЛЬГА | I3: Стандартный | J3: Оплата по счету № 15349 от 23 июля 2026 г. Агентский договор № ДА-25/47 по организации перевозок пассажиров от 18.12.2024 516000-00 руб. Без налога (НДС) | K3: 46233 | L3: Иноземцева Марина Сергеевна
A4: Оплата поставщикам Прочие поставщики 4121 | B4: 18000 | C4: АЛЬТАИР ООО (ИНН 6150056780) | D4: СИ00-034965 | E4: 09.09.2026 5:11:02 | F4: Согласована | G4: Сервис-Интегратор ООО | H4: ДТ МУРАВЛЕНКО | I4: Стандартный | J4: Оплата по Счет №М28440 от 01.09.26г Поверка тахографа на 6 ТС Сумма 18 000-00руб В т.ч. НДС(5%) 857-14руб | K4: 46274 | L4: Ермакова Алёна Викторовна
A5: Оплата поставщикам Прочие поставщики 4121 | B5: 124178 | C5: ДАЛЬМЕД ООО | D5: СИ00-035131 | E5: 10.09.2026 8:01:02 | F5: Согласована | G5: Сервис-Интегратор ООО | H5: ДТ ЭЛЬГА | I5: Стандартный | J5: Оплата по акту №1230 от 31.08.2026 124178-00 руб. Соглашение о передаче Договора № 78 на оказание медицинских услуг во врачебной амбулатории от 14.11.2022 Без налога (НДС) | K5: 46280 | L5: Иноземцева Марина Сергеевна
A6: Оплата поставщикам Прочие поставщики 4121 | B6: 1400 | C6: ДАЛЬМЕД ООО | D6: СИ00-035133 | E6: 10.09.2026 8:10:09 | F6: Согласована | G6: Сервис-Интегратор ООО | H6: ДТ ЭЛЬГА | I6: Стандартный | J6: Оплата по с/ф № 1231 от 31.08.2026 г Соглашение о передаче Договора № 81/23 оказания услуг по проведению тестирования на коровирусную инфекцию от 10.03.2023 1400-00 руб. Без налога (НДС) | K6: 46280 | L6: Иноземцева Марина Сергеевна
A7: Оплата поставщикам Перелеты и тревел-поставщики 4121 | B7: 26000 | C7: РАТЕЛ АВИАСЕРВИС ООО | D7: СИ00-034201 | E7: 03.09.2026 8:33:42 | F7: Согласована | G7: Сервис-Интегратор ООО | H7: ДТ ЭЛЬГА | I7: Стандартный | J7: Оплата по счету № 18824 от 02 сентября 2026 г. Агентский договор № ДА-25/47 по организации перевозок пассажиров от 18.12.2024 26000-00 руб. Без налога (НДС) | K7: 46312 | L7: Иноземцева Марина Сергеевна
A8: Оплата поставщикам Транспортные услуги 4121 | B8: 80000 | C8: РН-Ванкор ООО | D8: СИ00-036332 | E8: 16.09.2026 8:14:09 | F8: Согласована | G8: Сервис-Интегратор ООО | H8: ДТ ТУРУХАНСК | I8: Стандартный | J8: Оплата по Договор № В066023/4236Д на оказание услуг хранения ТМЦ и на выполнение погрузочно-разгрузочных работ от 24.11.2024 80000-00 руб. В т.ч. НДС (22%) 14426-23 руб. Аванс по договору № В066023/4236Д | K8: 46281 | L8: Кокоулин Дмитрий Геннадьевич
A9: Оплата поставщикам Прочие поставщики 4121 | B9: 125174.35 | C9: МОСКОВСКИЙ МЕТРОПОЛИТЕН ГУП | D9: СИ00-033245 | E9: 27.08.2026 17:36:48 | F9: Согласована | G9: Сервис-Интегратор ООО | H9: ДТ КАЗАНЬ | I9: Стандартный | J9: Оплата по Договор № 5398м на оказание услуг по обучению от 03.09.2025 по счету №11 от 19.08.2026 на сумму 125174-35 руб. Без налога (НДС) | K9: 46261 | L9: Семенов Владимир Александрович
A10: Оплата поставщикам Запчасти, ремонт 4121 | B10: 51750 | C10: Спец Ремонт 24 ООО | D10: СИ00-034061 | E10: 02.09.2026 11:27:50 | F10: Согласована | G10: Сервис-Интегратор ООО | H10: ДТ ТУРУХАНСК | I10: Стандартный | J10: "Предоплата за ремонт ДВС KUBOTA по счету №53 от 28.08.2026" | K10: 46268 | L10: Зубков Иван Александрович
A11: Оплата поставщикам Запчасти, ремонт 4121 | B11: 194349.8 | C11: Спец Ремонт 24 ООО | D11: СИ00-034055 | E11: 02.09.2026 11:15:54 | F11: Согласована | G11: Сервис-Интегратор ООО | H11: ДТ ТУРУХАНСК | I11: Стандартный | J11: Оплата по Договор № СР24-5 на оказание услуг по ремонту агрегата/ТС от 15.04.2026 194349-80 руб. В т.ч. НДС (22%) 35046-69 руб. | K11: 46268 | L11: Зубков Иван Александрович
A12: Оплата поставщикам Спецодежда 4121 | B12: 38887.5 | C12: ГК АВАНГАРД СЭЙФЕТИ ООО | D12: СИ00-033383 | E12: 28.08.2026 11:47:45 | F12: Согласована | G12: Сервис-Интегратор ООО | H12: ДТ НОВЫЙ УРЕНГОЙ | I12: Стандартный | J12: Предоплата по Спецификациям Договора поставки № 162 от 22.04.2021 за спецодежду для сотрудников 38887-50 руб. В т.ч. НДС (22%) 7012-50 руб. | K12: 46262 | L12: Винокуров Роман Александрович
A13: Оплата поставщикам Спецодежда 4121 | B13: 445472.02 | C13: ФИРМА ТЕХНОАВИА ПВ ООО | D13: СИ00-035555 | E13: 11.09.2026 14:49:42 | F13: Согласована | G13: Сервис-Интегратор ООО | H13: ДТ НОВЫЙ УРЕНГОЙ | I13: Стандартный | J13: Предоплата по Спецификациям Договора поставки № 22 от 29.03.2018 за спецодежду для сотрудников 445472-02 руб. В т.ч. НДС (22%) 80331-02 руб. | K13: 46276 | L13: Винокуров Роман Александрович
... A21: Оплата поставщикам Запчасти, ремонт 4121 | B21: 48100 | C21: АВАНГАРД АВТО ООО | D21: СИ00-032296 | E21: 21.08.2026 8:50:02 | F21: Согласована | G21: Сервис-Интегратор ООО | H21: ДТ ТОБОЛЬСК | I21: Стандартный | J21: Оплата по накладной №459 от 21.07.2026 42900-00 руб., накладной №460 от 21.07.2026 5200-00 руб. В т.ч. НДС (22%) 8673-77 руб. З/части д/сл. авто. | K21: 46269 | L21: Калачинская Надежда Ивановна
A30: Сводная таблица оплат по подразделениям
A32: Контрагент | B32: ДТ КАЗАНЬ | C32: ДТ МУРАВЛЕНКО | D32: ДТ НОВЫЙ УРЕНГОЙ | E32: ДТ ТОБОЛЬСК | F32: ДТ ТУРУХАНСК | G32: ДТ ЭЛЬГА | H32: Итого | I32: Пояснение
A33: АВАНГАРД АВТО ООО | B33: 0 | C33: 0 | D33: 0 | E33: 382785.12 | F33: 0 | G33: 0 | H33: 382785.12 | I33: Запчасти
A34: АЛЬТАИР ООО (ИНН 6150056780) | B34: 0 | C34: 18000 | D34: 0 | E34: 0 | F34: 0 | G34: 0 | H34: 18000 | I34: Поверка тахографов
A35: ГК АВАНГАРД СЭЙФЕТИ ООО | B35: 0 | C35: 0 | D35: 38887.5 | E35: 0 | F35: 0 | G35: 0 | H35: 38887.5 | I35: Спецодежда
A36: ДАЛЬМЕД ООО | B36: 0 | C36: 0 | D36: 0 | E36: 0 | F36: 0 | G36: 125578 | H36: 125578 | I36: Медосмотры
A37: МОСКОВСКИЙ МЕТРОПОЛИТЕН ГУП | B37: 125174.35 | C37: 0 | D37: 0 | E37: 0 | F37: 0 | G37: 0 | H37: 125174.35 | I37: Обучение
A38: РАТЕЛ АВИАСЕРВИС ООО | B38: 0 | C38: 0 | D38: 0 | E38: 0 | F38: 0 | G38: 542000 | H38: 542000 | I38: Перелеты
A39: РН-Ванкор ООО | B39: 0 | C39: 0 | D39: 0 | E39: 0 | F39: 80000 | G39: 0 | H39: 80000 | I39: Погрузочно-разгрузочные работы
A40: Спец Ремонт 24 ООО | B40: 0 | C40: 0 | D40: 0 | E40: 0 | F40: 246099.8 | G40: 0 | H40: 246099.8 | I40: ТО и ремонты
A41: УФК по Нижегородской области (Павловское РОСП ГУ ФССП по Нижегородской области, л/с 05321845290) | B41: 0 | C41: 0 | D41: 0 | E41: 0 | F41: 1000000 | G41: 0 | H41: 1000000 | I41: Оплата в адрес пристава (СОЮЗ-ЭНЕРГО)
A42: ФИРМА ТЕХНОАВИА ПВ ООО | B42: 0 | C42: 0 | D42: 445472.02 | E42: 0 | F42: 0 | G42: 0 | H42: 445472.02 | I42: Спецодежда
A43: ИТОГО | B43: 125174.35 | C43: 18000 | D43: 484359.52 | E43: 382785.12 | F43: 1326099.8 | G43: 667578 | H43: 3003996.8
